gpt_data_dictionary/__init__.py
gpt_data_dictionary-0.1.0.dist-info/LICENSE
gpt_data_dictionary-0.1.0.dist-info/METADATA
gpt_data_dictionary-0.1.0.dist-info/WHEEL
gpt_data_dictionary-0.1.0.dist-info/RECORD
