Metadata-Version: 2.1
Name: gpt-data-dictionary
Version: 0.1.0
Summary: data-dictionary is a Python package that automates the creation of data dictionaries utilizing LLM. It generates human-readable variable names and provides comprehensive metadata, making it an essential tool for data management, enhancing data interpretability and quality assurance.
License: Apache-2.0
Author: leehanchung
Author-email: lee.hanchung@gmail.com
Requires-Python: >=3.10,<4.0
Classifier: License :: OSI Approved :: Apache Software License
Classifier: Programming Language :: Python :: 3
Classifier: Programming Language :: Python :: 3.10
Classifier: Programming Language :: Python :: 3.11
Classifier: Topic :: Software Development :: Libraries :: Python Modules
Requires-Dist: fire (>=0.5.0,<0.6.0)
Requires-Dist: jinja2 (>=3.1.2,<4.0.0)
Requires-Dist: langchain (>=0.0.285,<0.0.286)
Requires-Dist: openai (>=0.28.0,<0.29.0)
Requires-Dist: pandas (>=2.1.0,<3.0.0)
Requires-Dist: pydantic (>=2.3.0,<3.0.0)
Requires-Dist: python-dotenv (>=1.0.0,<2.0.0)
